sagemaker/__init__.py
sagemaker/hyperpod/__init__.py
sagemaker/hyperpod/cli/__init__.py
sagemaker/hyperpod/cli/cluster_stack_utils.py
sagemaker/hyperpod/cli/cluster_utils.py
sagemaker/hyperpod/cli/common_utils.py
sagemaker/hyperpod/cli/hyp_cli.py
sagemaker/hyperpod/cli/inference_utils.py
sagemaker/hyperpod/cli/init_utils.py
sagemaker/hyperpod/cli/training_utils.py
sagemaker/hyperpod/cli/type_handler_utils.py
sagemaker/hyperpod/cli/utils.py
sagemaker/hyperpod/cli/clients/__init__.py
sagemaker/hyperpod/cli/clients/kubernetes_client.py
sagemaker/hyperpod/cli/commands/__init__.py
sagemaker/hyperpod/cli/commands/cluster.py
sagemaker/hyperpod/cli/commands/cluster_stack.py
sagemaker/hyperpod/cli/commands/inference.py
sagemaker/hyperpod/cli/commands/init.py
sagemaker/hyperpod/cli/commands/training.py
sagemaker/hyperpod/cli/constants/__init__.py
sagemaker/hyperpod/cli/constants/command_constants.py
sagemaker/hyperpod/cli/constants/exception_constants.py
sagemaker/hyperpod/cli/constants/hyperpod_instance_types.py
sagemaker/hyperpod/cli/constants/init_constants.py
sagemaker/hyperpod/cli/constants/kueue_constants.py
sagemaker/hyperpod/cli/constants/pytorch_constants.py
sagemaker/hyperpod/cli/service/__init__.py
sagemaker/hyperpod/cli/service/cancel_training_job.py
sagemaker/hyperpod/cli/service/discover_namespaces.py
sagemaker/hyperpod/cli/service/exec_command.py
sagemaker/hyperpod/cli/service/get_logs.py
sagemaker/hyperpod/cli/service/get_namespaces.py
sagemaker/hyperpod/cli/service/get_training_job.py
sagemaker/hyperpod/cli/service/list_pods.py
sagemaker/hyperpod/cli/service/list_training_jobs.py
sagemaker/hyperpod/cli/service/self_subject_access_review.py
sagemaker/hyperpod/cli/templates/__init__.py
sagemaker/hyperpod/cli/validators/__init__.py
sagemaker/hyperpod/cli/validators/cluster_validator.py
sagemaker/hyperpod/cli/validators/job_validator.py
sagemaker/hyperpod/cli/validators/validator.py
sagemaker/hyperpod/cluster_management/__init__.py
sagemaker_hyperpod-3.3.0.dist-info/licenses/LICENSE
sagemaker_hyperpod-3.3.0.dist-info/licenses/NOTICE
sagemaker_hyperpod-3.3.0.dist-info/METADATA
sagemaker_hyperpod-3.3.0.dist-info/WHEEL
sagemaker_hyperpod-3.3.0.dist-info/entry_points.txt
sagemaker_hyperpod-3.3.0.dist-info/top_level.txt
sagemaker_hyperpod-3.3.0.dist-info/zip-safe
sagemaker_hyperpod-3.3.0.dist-info/RECORD
