Metadata-Version: 2.4
Name: sagemaker-hyperpod
Version: 3.3.0
Summary: Amazon SageMaker HyperPod SDK and CLI
Home-page: https://github.com/aws/sagemaker-hyperpod-cli
Author: Amazon Web Services
License: Apache-2.0
Classifier: Development Status :: 4 - Beta
Classifier: Intended Audience :: Developers
Classifier: License :: OSI Approved :: Apache Software License
Classifier: Programming Language :: Python :: 3
Classifier: Programming Language :: Python :: 3.8
Classifier: Programming Language :: Python :: 3.9
Classifier: Programming Language :: Python :: 3.10
Classifier: Programming Language :: Python :: 3.11
Requires-Python: >=3.8
License-File: LICENSE
License-File: NOTICE
Requires-Dist: click==8.1.7
Requires-Dist: awscli>=1.34.9
Requires-Dist: awscli-cwlogs>=1.4.6
Requires-Dist: boto3<2.0,>=1.35.3
Requires-Dist: botocore>=1.35.6
Requires-Dist: kubernetes==33.1.0
Requires-Dist: pyyaml==6.0.2
Requires-Dist: ratelimit==2.2.1
Requires-Dist: tabulate==0.9.0
Requires-Dist: itables>=2.2.2
Requires-Dist: jinja2>=3.1.2
Requires-Dist: ipywidgets>=8.1.7
Requires-Dist: hydra-core==1.3.2
Requires-Dist: omegaconf==2.3
Requires-Dist: pynvml==11.4.1
Requires-Dist: requests==2.32.4
Requires-Dist: tqdm==4.66.5
Requires-Dist: zstandard==0.15.2
Requires-Dist: pytest==8.3.2
Requires-Dist: pytest-cov==5.0.0
Requires-Dist: pytest-order==1.3.0
Requires-Dist: pytest-dependency==0.6.0
Requires-Dist: tox==4.18.0
Requires-Dist: ruff==0.6.2
Requires-Dist: hera-workflows==5.16.3
Requires-Dist: sagemaker-core<2.0.0
Requires-Dist: pydantic<3.0.0,>=2.10.6
Requires-Dist: hyperpod-pytorch-job-template<2.0.0,>=1.0.0
Requires-Dist: hyperpod-custom-inference-template<2.0.0,>=1.0.0
Requires-Dist: hyperpod-jumpstart-inference-template<2.0.0,>=1.0.0
Requires-Dist: hyperpod-cluster-stack-template<2.0.0,>=1.0.0
Dynamic: home-page
Dynamic: license-file
Dynamic: requires-dist
Dynamic: requires-python
